MANIFEST.in
README.txt
setup.cfg
setup.py
ToscaWidgets.egg-info/PKG-INFO
ToscaWidgets.egg-info/SOURCES.txt
ToscaWidgets.egg-info/dependency_links.txt
ToscaWidgets.egg-info/entry_points.txt
ToscaWidgets.egg-info/namespace_packages.txt
ToscaWidgets.egg-info/not-zip-safe
ToscaWidgets.egg-info/requires.txt
ToscaWidgets.egg-info/top_level.txt
tw/__init__.py
tw/api.py
tw/paste_template.py
tw/release.py
tw/core/__init__.py
tw/core/base.py
tw/core/command.py
tw/core/engine_plugin.py
tw/core/exceptions.py
tw/core/js.py
tw/core/mako_util.py
tw/core/meta.py
tw/core/middleware.py
tw/core/registry.py
tw/core/resource_injector.py
tw/core/resources.py
tw/core/server.py
tw/core/testutil.py
tw/core/util.py
tw/core/view.py
tw/mods/__init__.py
tw/mods/base.py
tw/mods/cp2.py
tw/mods/cp3.py
tw/mods/pylonshf.py
tw/mods/tg.py
tw/mods/wsgi.py
tw/paste_templates/__init__.py
tw/paste_templates/widget_template/MANIFEST.in_tmpl
tw/paste_templates/widget_template/setup.cfg_tmpl
tw/paste_templates/widget_template/setup.py_tmpl
tw/paste_templates/widget_template/+egg+.egg-info/paster_plugins.txt
tw/paste_templates/widget_template/docs/conf.py_tmpl
tw/paste_templates/widget_template/docs/index.rst_tmpl
tw/paste_templates/widget_template/tests/__init__.py_tmpl
tw/paste_templates/widget_template/tests/test_widget.py_tmpl
tw/paste_templates/widget_template/tw/__init__.py_tmpl
tw/paste_templates/widget_template/tw/+package+/__init__.py_tmpl
tw/paste_templates/widget_template/tw/+package+/release.py_tmpl
tw/paste_templates/widget_template/tw/+package+/samples.py_tmpl
tw/paste_templates/widget_template/tw/+package+/widgets.py_tmpl