Metadata-Version: 1.0
Name: ToscaWidgets
Version: 0.9.12
Summary: Web widget creation toolkit based on TurboGears widgets
Home-page: http://toscawidgets.org/
Author: Alberto Valverde Gonzalez
Author-email: alberto@toscat.net
License: MIT
Download-URL: http://toscawidgets.org/download/
Platform: UNKNOWN
Classifier: Development Status :: 4 - Beta
Classifier: Environment :: Web Environment
Classifier: Environment :: Web Environment :: ToscaWidgets
Classifier: Topic :: Software Development :: Libraries :: Python Modules
Classifier: Topic :: Internet :: WWW/HTTP :: WSGI
Classifier: Topic :: Internet :: WWW/HTTP :: WSGI :: Middleware
Classifier: Topic :: Software Development :: Widget Sets
Classifier: Intended Audience :: Developers
Classifier: License :: OSI Approved :: MIT License
Classifier: Operating System :: OS Independent
Classifier: Programming Language :: Python
